CHANGELOG.rst
LICENSE
MANIFEST.in
README.rst
setup.py
django_pyscss/__init__.py
django_pyscss/compiler.py
django_pyscss/compressor.py
django_pyscss/utils.py
django_pyscss.egg-info/PKG-INFO
django_pyscss.egg-info/SOURCES.txt
django_pyscss.egg-info/dependency_links.txt
django_pyscss.egg-info/not-zip-safe
django_pyscss.egg-info/requires.txt
django_pyscss.egg-info/top_level.txt
django_pyscss/extension/__init__.py
django_pyscss/extension/django.py
testproject/__init__.py
testproject/runtests.py
testproject/testapp1/__init__.py
testproject/testapp1/admin.py
testproject/testapp1/models.py
testproject/testapp1/tests.py
testproject/testapp1/views.py
testproject/testapp1/static/css/app1.scss
testproject/testapp2/__init__.py
testproject/testapp2/admin.py
testproject/testapp2/models.py
testproject/testapp2/tests.py
testproject/testapp2/views.py
testproject/testapp2/static/css/app2.scss
testproject/testproject/__init__.py
testproject/testproject/settings.py
testproject/testproject/urls.py
testproject/testproject/wsgi.py
testproject/testproject/static/css/_baz.scss
testproject/testproject/static/css/bar.scss
testproject/testproject/static/css/css_file.css
testproject/testproject/static/css/dot.file.scss
testproject/testproject/static/css/foo.scss
testproject/testproject/static/css/path_conflict.scss
testproject/testproject/static/css/sass_file.sass
testproject/testproject/static/css/path_conflict/content.scss
testproject/testproject/static/css/prefixed/baz.scss
testproject/testproject/static/css/sub/_spam.scss
testproject/testproject/static/css/sub/from_parent.scss
testproject/testproject/static/images/loading.gif
testproject/testproject/static/images/icons/widget-google-map.png
testproject/testproject/static/images/icons/widget-skull-and-crossbones.png
tests/__init__.py
tests/test_compressor.py
tests/test_scss.py
tests/utils.py