Metadata-Version: 2.1
Name: django-pyscss
Version: 2.0.3
Summary: Makes it easier to use PySCSS in Django.
Home-page: https://github.com/fusionbox/django-pyscss
Author: Fusionbox, Inc.
Author-email: programmers@fusionbox.com
Keywords: django css scss sass pyscss compressor
Classifier: Development Status :: 4 - Beta
Classifier: Framework :: Django
Classifier: Intended Audience :: Developers
Classifier: License :: OSI Approved :: BSD License
Classifier: Topic :: Internet :: WWW/HTTP
Classifier: Programming Language :: Python
Classifier: Programming Language :: Python :: 2.6
Classifier: Programming Language :: Python :: 2.7
Classifier: Programming Language :: Python :: 3.3
Classifier: Programming Language :: Python :: 3.4
License-File: LICENSE
